mmry/__init__.py
mmry/cache.py
mmry-0.0.9.dist-info/METADATA
mmry-0.0.9.dist-info/WHEEL
mmry-0.0.9.dist-info/top_level.txt
mmry-0.0.9.dist-info/RECORD
