Metadata-Version: 2.1
Name: mmry
Version: 0.0.9
Summary: Unix disk cache for software 2.0
Author-email: Jason Wilkes <notarealdeveloper@gmail.com>, Ramya Kottapalli <rskottap@gmail.com>
Project-URL: source, https://github.com/notarealdeveloper/mmry
Project-URL: download, https://pypi.org/project/mmry/#files
